card/__init__.py
card/card.py
card/face.py
card/suit.py
card_tb-0.0.4.dist-info/LICENSE
card_tb-0.0.4.dist-info/METADATA
card_tb-0.0.4.dist-info/WHEEL
card_tb-0.0.4.dist-info/top_level.txt
card_tb-0.0.4.dist-info/RECORD
