Metadata-Version: 2.1
Name: card_tb
Version: 0.0.4
Summary: A simple card package which has the types card, face, and suit.
Author-email: Thomas Brumbaugh <thomas.william.brumbaugh@gmail.com>
Project-URL: Homepage, https://github.com/card_tb
Project-URL: Issues, https://github.com/pypa/card_tb/issues
Classifier: Programming Language :: Python :: 3
Classifier: License :: OSI Approved :: MIT License
Classifier: Operating System :: OS Independent
Requires-Python: >=3.8
License-File: LICENSE
